dominos_common/__init__.py
dominos_common/src/__init__.py
dominos_common/src/db_helper/__init__.py
dominos_common/src/db_helper/address_model.py
dominos_common/src/db_helper/database.py
dominos_common/src/db_helper/item_model.py
dominos_common/src/db_helper/order_model.py
dominos_common/src/db_helper/restaurant_model.py
dominos_common/src/db_helper/user_model.py
dominos_common-0.0.17.dist-info/METADATA
dominos_common-0.0.17.dist-info/WHEEL
dominos_common-0.0.17.dist-info/top_level.txt
dominos_common-0.0.17.dist-info/RECORD
