Metadata-Version: 2.1
Name: dominos_common
Version: 0.0.17
Summary: Share utilities and models across the Dominos app
Home-page: https://github.com/dekelbyz/dominos-common
Author: Dekel Bayazi
Author-email: bayazi455@gmail.com
License: MIT
Classifier: License :: OSI Approved :: MIT License
Classifier: Programming Language :: Python :: 3.10
Classifier: Operating System :: OS Independent
Requires-Python: >=3.10
Requires-Dist: bson >=0.5.10
Requires-Dist: SQLAlchemy >=2.0.30
Requires-Dist: psycopg2-binary >=2.9.9
Provides-Extra: dev
Requires-Dist: pytest >=7.0 ; extra == 'dev'
Requires-Dist: twine >=4.0.2 ; extra == 'dev'
